setup.py
./song2/__init__.py
./song2/types.py
song2.egg-info/PKG-INFO
song2.egg-info/SOURCES.txt
song2.egg-info/dependency_links.txt
song2.egg-info/top_level.txt
song2.egg-info/zip-safe