Metadata-Version: 1.1
Name: song2
Version: 0.1.0
Summary: Typesafe/Immutable schema for dict object
Home-page: UNKNOWN
Author: Takumakanari
Author-email: chemtrails.t@gmail.com
License: MIT
Keywords: schema dict immutable typesafe
Platform: UNKNOWN
Classifier: Development Status :: 4 - Beta
Classifier: Environment :: Web Environment
Classifier: Intended Audience :: Developers
Classifier: License :: OSI Approved :: MIT License
Classifier: Operating System :: OS Independent
Classifier: Programming Language :: Python
Classifier: Programming Language :: Python :: 2
Classifier: Programming Language :: Python :: 2.7
Classifier: Topic :: Software Development :: Libraries :: Python Modules
